str_authFr/__init__.py
str_authFr/authenticate.py
str_authFr/exceptions.py
str_authFr/hasher.py
str_authFr/utils.py
str_authFr-2022.0.1.dist-info/LICENSE
str_authFr-2022.0.1.dist-info/METADATA
str_authFr-2022.0.1.dist-info/WHEEL
str_authFr-2022.0.1.dist-info/top_level.txt
str_authFr-2022.0.1.dist-info/RECORD
