Metadata-Version: 2.1
Name: str-authFr
Version: 2022.0.1
Summary: A secure authentication module to validate user credentials in a Streamlit application created by Mohammad Khorasani with widgets texts translated in french
Author: Mohammad Khorasani
Author-email: khorasani.mohammad@gmail.com
Maintainer-email: Arsène BAKANDAKAN <contactjrdk@gmail.com>
License: Apache License
Project-URL: homepage, https://github.com/mkhorasani/Streamlit-Authenticator
Keywords: Python,Streamlit,Authentication,Components
Classifier: Development Status :: 4 - Beta
Classifier: Programming Language :: Python
Classifier: License :: OSI Approved :: MIT License
Classifier: Operating System :: OS Independent
Requires-Python: >=3.6
License-File: LICENSE
Requires-Dist: PyJWT (>=2.3.0)
Requires-Dist: bcrypt (>=3.1.7)
Requires-Dist: PyYAML (>=5.3.1)
Requires-Dist: streamlit (>=0.86)
Requires-Dist: extra-streamlit-components (>=0.1.55)
